pyidh/__init__.py
pyidh/pyidh.py
pyidh/win_amd64/libcrypto-3-x64.dll
pyidh/win_amd64/libidh.dll
pyidh-0.1.8.dist-info/METADATA
pyidh-0.1.8.dist-info/WHEEL
pyidh-0.1.8.dist-info/top_level.txt
pyidh-0.1.8.dist-info/RECORD
