Metadata-Version: 2.4
Name: pyidh
Version: 0.1.8
Summary: Python wrapper for Industry Data Hub (win_amd64)
Home-page: https://github.com/ymwang78/IndustryDataHub
Author: Yongming Wang
Author-email: wangym@gmail.com
Project-URL: Bug Reports, https://github.com/ymwang78/IndustryDataHub/issues
Project-URL: Source, https://github.com/ymwang78/IndustryDataHub
Project-URL: Documentation, https://github.com/ymwang78/IndustryDataHub/wiki
Keywords: industrial automation,data communication,OPC,modbus,multi-platform
Classifier: Programming Language :: Python :: 3
Classifier: Programming Language :: Python :: 3 :: Only
Classifier: License :: OSI Approved :: MIT License
Classifier: Development Status :: 4 - Beta
Classifier: Intended Audience :: Developers
Classifier: Topic :: Software Development :: Libraries :: Python Modules
Classifier: Topic :: System :: Hardware
Classifier: Topic :: Communications
Classifier: Operating System :: Microsoft :: Windows
Requires-Python: >=3.8
Requires-Dist: pywin32>=305
Dynamic: author
Dynamic: author-email
Dynamic: classifier
Dynamic: description
Dynamic: description-content-type
Dynamic: home-page
Dynamic: keywords
Dynamic: project-url
Dynamic: requires-dist
Dynamic: requires-python
Dynamic: summary
